l33tapi/__init__.py
l33tapi/api.py
l33tapi-1.0.3.dist-info/LICENSE
l33tapi-1.0.3.dist-info/METADATA
l33tapi-1.0.3.dist-info/WHEEL
l33tapi-1.0.3.dist-info/top_level.txt
l33tapi-1.0.3.dist-info/RECORD
