Metadata-Version: 2.1
Name: l33tapi
Version: 1.0.3
Summary: A l33t Api Wrapper
Home-page: https://github.com/lol-1-afk/l33t-API-Wrapper
Author: requestsn
License: UNKNOWN
Platform: UNKNOWN
Classifier: Programming Language :: Python :: 3.9
Classifier: License :: OSI Approved :: MIT License
Classifier: Operating System :: OS Independent
Requires-Python: >=3.6
License-File: LICENSE
Requires-Dist: requests (>=2.21.0)
